[
  {
    "id": "317149692887",
    "user_id": "133400606",
    "user_login": "slushieghost",
    "user_name": "SlushieGhost",
    "game_id": "27471",
    "game_name": "Minecraft",
    "type": "live",
    "title": "✧ Meet your fluffy moth Sumire!! | adVenture: Ascension ep 1✧ !lurk !merch !throne !clip",
    "viewer_count": 22,
    "started_at": "2026-03-21T19:00:50Z",
    "language": "en",
    "thumbnail_url": "https://static-cdn.jtvnw.net/previews-ttv/live_user_slushieghost-{width}x{height}.jpg",
    "tag_ids": [],
    "tags": [
      "Comfy",
      "LGBT",
      "Nonbinary",
      "VTuber",
      "SpanishAndEnglish",
      "ENVtuber",
      "Hispanic",
      "ADHD",
      "Bilingual",
      "adVAscension"
    ],
    "is_mature": true,
    "profile_image_url": "https://static-cdn.jtvnw.net/jtv_user_pictures/7f48840f-5f89-432b-981b-c1e575eccae8-profile_image-300x300.png"
  },
  {
    "id": "317796757212",
    "user_id": "100422083",
    "user_login": "plompers",
    "user_name": "Plompers",
    "game_id": "1846293708",
    "game_name": "Fields of Mistria",
    "type": "live",
    "title": "i don't have pokopia so mistria here i come ✧",
    "viewer_count": 14,
    "started_at": "2026-03-21T21:07:38Z",
    "language": "en",
    "thumbnail_url": "https://static-cdn.jtvnw.net/previews-ttv/live_user_plompers-{width}x{height}.jpg",
    "tag_ids": [],
    "tags": [
      "LurkerFriendly",
      "SafeSpace",
      "English",
      "Vtuber",
      "Comfy",
      "Cozy",
      "Asian",
      "vcanada"
    ],
    "is_mature": true,
    "profile_image_url": "https://static-cdn.jtvnw.net/jtv_user_pictures/e86c1253-38fe-43a5-b406-139c80c7d7ca-profile_image-300x300.png"
  },
  {
    "id": "318346653658",
    "user_id": "710026427",
    "user_login": "wallowsett",
    "user_name": "WallowSett",
    "game_id": "27471",
    "game_name": "Minecraft",
    "type": "live",
    "title": "[adVenture: Ascension] Magnolia's glorious start of her two week minecraft phase c:",
    "viewer_count": 6,
    "started_at": "2026-03-21T20:45:08Z",
    "language": "en",
    "thumbnail_url": "https://static-cdn.jtvnw.net/previews-ttv/live_user_wallowsett-{width}x{height}.jpg",
    "tag_ids": [],
    "tags": [
      "Vtuber",
      "ComfyCafe",
      "English",
      "Retro",
      "RP",
      "advascension",
      "ViewerRewards"
    ],
    "is_mature": true,
    "profile_image_url": "https://static-cdn.jtvnw.net/jtv_user_pictures/ca58bc11-b3fa-4d36-b0d1-cc772c642e3a-profile_image-300x300.png"
  },
  {
    "id": "318456267611",
    "user_id": "73150212",
    "user_login": "xionfox",
    "user_name": "XionFox",
    "game_id": "27471",
    "game_name": "Minecraft",
    "type": "live",
    "title": "[CRESTFALL ACADEMY/V-ORIGINS SMP] Getting our pokemon groove going then it's event time!",
    "viewer_count": 6,
    "started_at": "2026-03-21T23:59:11Z",
    "language": "en",
    "thumbnail_url": "https://static-cdn.jtvnw.net/previews-ttv/live_user_xionfox-{width}x{height}.jpg",
    "tag_ids": [],
    "tags": [
      "vtuber",
      "voiceacting",
      "fox",
      "foxtuber",
      "scuff",
      "chatting",
      "English",
      "Japanese",
      "ViewerRewards"
    ],
    "is_mature": false,
    "profile_image_url": "https://static-cdn.jtvnw.net/jtv_user_pictures/93d2ee3a-dc14-4abb-abd7-c6a5922d568b-profile_image-300x300.jpeg"
  },
  {
    "id": "315388148584",
    "user_id": "209565401",
    "user_login": "aidenchii",
    "user_name": "AidenChii",
    "game_id": "509658",
    "game_name": "Just Chatting",
    "type": "live",
    "title": "🦝| Just Chatting | im chatting all over then vorigins later w/ @kenjamincity | !Discord | !Socials | 🦝👟👑",
    "viewer_count": 5,
    "started_at": "2026-03-21T22:55:09Z",
    "language": "en",
    "thumbnail_url": "https://static-cdn.jtvnw.net/previews-ttv/live_user_aidenchii-{width}x{height}.jpg",
    "tag_ids": [],
    "tags": [
      "Austrailan",
      "Vtuber",
      "Raccoon",
      "LOUD",
      "Yapper",
      "English"
    ],
    "is_mature": false,
    "profile_image_url": "https://static-cdn.jtvnw.net/jtv_user_pictures/49de8b12-0fa4-45ba-b7d9-edcc115ba796-profile_image-300x300.png"
  },
  {
    "id": "317797532508",
    "user_id": "228334289",
    "user_login": "rams_404_",
    "user_name": "Rams_404_",
    "game_id": "515025",
    "game_name": "Overwatch",
    "type": "live",
    "title": "✨[18+ Eng/Esp] ✨I NEED HEALING✨ !socials !discord !lurk !SMP @rams_404_ ✨",
    "viewer_count": 4,
    "started_at": "2026-03-21T22:04:36Z",
    "language": "en",
    "thumbnail_url": "https://static-cdn.jtvnw.net/previews-ttv/live_user_rams_404_-{width}x{height}.jpg",
    "tag_ids": [],
    "tags": [
      "Vtuber",
      "English",
      "spanish",
      "Cozy",
      "feet",
      "chaos",
      "femboy",
      "DropsEnabled"
    ],
    "is_mature": false,
    "profile_image_url": "https://static-cdn.jtvnw.net/jtv_user_pictures/675646a1-b8ac-4bda-a242-2fda8f4e17a3-profile_image-300x300.png"
  },
  {
    "id": "315429359593",
    "user_id": "95084465",
    "user_login": "deltarious5",
    "user_name": "Deltarious5",
    "game_id": "27471",
    "game_name": "Minecraft",
    "type": "live",
    "title": "balls smacked, time to smack blocks! [!discord] [!dubby] [18+]",
    "viewer_count": 2,
    "started_at": "2026-03-21T20:04:01Z",
    "language": "en",
    "thumbnail_url": "https://static-cdn.jtvnw.net/previews-ttv/live_user_deltarious5-{width}x{height}.jpg",
    "tag_ids": [],
    "tags": [
      "NewZealand",
      "Casual",
      "ADHD",
      "English",
      "Vtuber",
      "NoBackseatingUnlessAsked",
      "18pluschannel",
      "cosplayer",
      "crossdresser",
      "Anime"
    ],
    "is_mature": false,
    "profile_image_url": "https://static-cdn.jtvnw.net/jtv_user_pictures/bae917c1-464e-4eae-a727-5d4b761fac21-profile_image-300x300.png"
  },
  {
    "id": "318452322523",
    "user_id": "813947034",
    "user_login": "starfastwolf",
    "user_name": "starfastwolf",
    "game_id": "66366",
    "game_name": "War Thunder",
    "type": "live",
    "title": "Saturday chaotic warthunder vibes",
    "viewer_count": 1,
    "started_at": "2026-03-21T20:50:41Z",
    "language": "en",
    "thumbnail_url": "https://static-cdn.jtvnw.net/previews-ttv/live_user_starfastwolf-{width}x{height}.jpg",
    "tag_ids": [],
    "tags": [
      "English",
      "Vtuber",
      "justcchatting",
      "warrthunder",
      "18plusstream"
    ],
    "is_mature": false,
    "profile_image_url": "https://static-cdn.jtvnw.net/jtv_user_pictures/15c1f727-32b2-483b-a46f-d4d7dc929b13-profile_image-300x300.png"
  },
  {
    "id": "317796923356",
    "user_id": "171862865",
    "user_login": "kingthekeeper",
    "user_name": "KingTheKeeper",
    "game_id": "1147745783",
    "game_name": "Inscryption",
    "type": "live",
    "title": "Haven't touched these cards in a long time",
    "viewer_count": 1,
    "started_at": "2026-03-21T21:19:22Z",
    "language": "en",
    "thumbnail_url": "https://static-cdn.jtvnw.net/previews-ttv/live_user_kingthekeeper-{width}x{height}.jpg",
    "tag_ids": [],
    "tags": [
      "English",
      "VTuber",
      "lgbtq"
    ],
    "is_mature": false,
    "profile_image_url": "https://static-cdn.jtvnw.net/jtv_user_pictures/7d897685-7b22-405d-9f96-b8a116d7f41a-profile_image-300x300.png"
  },
  {
    "id": "317862010590",
    "user_id": "240610101",
    "user_login": "shatteredsoullive",
    "user_name": "shatteredsoullive",
    "game_id": "1936054038",
    "game_name": "Little Nightmares III",
    "type": "live",
    "title": "Diving into a little nightmare with @cilaires",
    "viewer_count": 1,
    "started_at": "2026-03-22T00:15:09Z",
    "language": "en",
    "thumbnail_url": "https://static-cdn.jtvnw.net/previews-ttv/live_user_shatteredsoullive-{width}x{height}.jpg",
    "tag_ids": [],
    "tags": [
      "ADHD",
      "Variety",
      "bipocstreamer",
      "English",
      "TwitchGuildUnity",
      "LatinUnityGuild",
      "Chaotic",
      "PeanutButterGang",
      "Rerun",
      "twitchprideguild"
    ],
    "is_mature": true,
    "profile_image_url": "https://static-cdn.jtvnw.net/jtv_user_pictures/7de01ff8-4534-4756-8acc-64c7796d17a3-profile_image-300x300.png"
  }
]