[
  {
    "id": "317450381911",
    "user_id": "133400606",
    "user_login": "slushieghost",
    "user_name": "SlushieGhost",
    "game_id": "511212",
    "game_name": "Subnautica: Below Zero",
    "type": "live",
    "title": "✧ Oh god please hold my hand qwq ✧ !lurk !merch !throne !clip",
    "viewer_count": 34,
    "started_at": "2026-04-16T23:06:26Z",
    "language": "en",
    "thumbnail_url": "https://static-cdn.jtvnw.net/previews-ttv/live_user_slushieghost-{width}x{height}.jpg",
    "tag_ids": [],
    "tags": [
      "Comfy",
      "LGBT",
      "Nonbinary",
      "VTuber",
      "SpanishAndEnglish",
      "ENVtuber",
      "Hispanic",
      "ADHD",
      "Bilingual",
      "YappingEncouraged"
    ],
    "is_mature": true,
    "profile_image_url": "https://static-cdn.jtvnw.net/jtv_user_pictures/6e8d14cb-b743-44f6-a457-b73f99024157-profile_image-300x300.png"
  },
  {
    "id": "318809158874",
    "user_id": "952513348",
    "user_login": "cabbytat",
    "user_name": "CabbyTat",
    "game_id": "490744",
    "game_name": "Stardew Valley",
    "type": "live",
    "title": "[18+] ON THE RANCH WITH @heyvelleity | STARDEW VALLEY",
    "viewer_count": 10,
    "started_at": "2026-04-16T23:50:44Z",
    "language": "en",
    "thumbnail_url": "https://static-cdn.jtvnw.net/previews-ttv/live_user_cabbytat-{width}x{height}.jpg",
    "tag_ids": [],
    "tags": [
      "Catboy",
      "BoyWife",
      "Anime",
      "Comfy",
      "LGBTQ",
      "English",
      "femboy",
      "Vtuber",
      "Chatting",
      "BackseatGamingAllowed"
    ],
    "is_mature": false,
    "profile_image_url": "https://static-cdn.jtvnw.net/jtv_user_pictures/653014f5-f4ef-4b21-ab71-333a28ca8cc8-profile_image-300x300.jpeg"
  },
  {
    "id": "318750653785",
    "user_id": "686234820",
    "user_login": "miyuwanchan",
    "user_name": "miyuwanchan",
    "game_id": "1950608914",
    "game_name": "Knights End",
    "type": "live",
    "title": "disgraced and disowned (in game) | !hug !discord",
    "viewer_count": 9,
    "started_at": "2026-04-17T00:56:43Z",
    "language": "en",
    "thumbnail_url": "https://static-cdn.jtvnw.net/previews-ttv/live_user_miyuwanchan-{width}x{height}.jpg",
    "tag_ids": [],
    "tags": [
      "Vtuber",
      "SafeSpace",
      "English",
      "Anime",
      "Live2D",
      "DogVtuber",
      "ENVtuber",
      "LGBTQPlus",
      "gyaru",
      "ComfyChaotic"
    ],
    "is_mature": false,
    "profile_image_url": "https://static-cdn.jtvnw.net/jtv_user_pictures/4a5300a0-d373-418f-ba3d-7fd592c2aa2f-profile_image-300x300.png"
  },
  {
    "id": "318182224604",
    "user_id": "228334289",
    "user_login": "rams_404_",
    "user_name": "Rams_404_",
    "game_id": "27471",
    "game_name": "Minecraft",
    "type": "live",
    "title": "✨[18+ Eng/Esp] ✨Stinky mines then crafts✨ !socials !discord !lurk !SMP @rams_404_ ✨",
    "viewer_count": 8,
    "started_at": "2026-04-16T22:24:05Z",
    "language": "en",
    "thumbnail_url": "https://static-cdn.jtvnw.net/previews-ttv/live_user_rams_404_-{width}x{height}.jpg",
    "tag_ids": [],
    "tags": [
      "Vtuber",
      "femboy",
      "English",
      "spanish",
      "18plus",
      "MaleVtuber",
      "chaos",
      "feet",
      "Cozy",
      "brat"
    ],
    "is_mature": false,
    "profile_image_url": "https://static-cdn.jtvnw.net/jtv_user_pictures/5ff8cef8-9174-48f4-a413-69e7514c2603-profile_image-300x300.png"
  },
  {
    "id": "318181397852",
    "user_id": "1142519722",
    "user_login": "triagesylphiel",
    "user_name": "TriageSylphiel",
    "game_id": "1044890345",
    "game_name": "Pokémon Infinite Fusion",
    "type": "live",
    "title": "BIRB STRUGGLES WITH RANDO NUZLOCKE | Pt. 2| !Clip !Discord",
    "viewer_count": 7,
    "started_at": "2026-04-16T21:29:44Z",
    "language": "en",
    "thumbnail_url": "https://static-cdn.jtvnw.net/previews-ttv/live_user_triagesylphiel-{width}x{height}.jpg",
    "tag_ids": [],
    "tags": [
      "Vtuber",
      "English",
      "birdtuber",
      "peepeepoopoo",
      "LGBTQFriendly",
      "indievtuber",
      "ENVtuber",
      "vtubers",
      "CloacaKing"
    ],
    "is_mature": false,
    "profile_image_url": "https://static-cdn.jtvnw.net/jtv_user_pictures/656f0ac1-dda4-421b-ba6c-5872f45058ce-profile_image-300x300.jpeg"
  },
  {
    "id": "318750809049",
    "user_id": "73150212",
    "user_login": "xionfox",
    "user_name": "XionFox",
    "game_id": "27471",
    "game_name": "Minecraft",
    "type": "live",
    "title": "[V-ORIGINS SMP] Having the hard conversations, Can we sort this out?",
    "viewer_count": 5,
    "started_at": "2026-04-17T01:02:19Z",
    "language": "en",
    "thumbnail_url": "https://static-cdn.jtvnw.net/previews-ttv/live_user_xionfox-{width}x{height}.jpg",
    "tag_ids": [],
    "tags": [
      "vtuber",
      "voiceacting",
      "fox",
      "foxtuber",
      "scuff",
      "chatting",
      "English",
      "Japanese",
      "ViewerRewards",
      "DropsEnabled"
    ],
    "is_mature": false,
    "profile_image_url": "https://static-cdn.jtvnw.net/jtv_user_pictures/93d2ee3a-dc14-4abb-abd7-c6a5922d568b-profile_image-300x300.jpeg"
  },
  {
    "id": "317450322519",
    "user_id": "686883069",
    "user_login": "eepysoma",
    "user_name": "EepySoma",
    "game_id": "492934",
    "game_name": "RESIDENT EVIL 7 biohazard",
    "type": "live",
    "title": "FINISHING RES EVIL 7",
    "viewer_count": 5,
    "started_at": "2026-04-16T23:01:19Z",
    "language": "en",
    "thumbnail_url": "https://static-cdn.jtvnw.net/previews-ttv/live_user_eepysoma-{width}x{height}.jpg",
    "tag_ids": [],
    "tags": [
      "English",
      "Vtuber",
      "ENVtuber",
      "indiegames",
      "Cozy",
      "fujoshi",
      "concubine",
      "LGBTQFriendly",
      "deadlock"
    ],
    "is_mature": false,
    "profile_image_url": "https://static-cdn.jtvnw.net/jtv_user_pictures/5b7e4298-5bea-46d5-84cb-9684152cb8aa-profile_image-300x300.png"
  },
  {
    "id": "318239404638",
    "user_id": "243161944",
    "user_login": "dracolicheren",
    "user_name": "DracolicheRen",
    "game_id": "1950608914",
    "game_name": "Knights End",
    "type": "live",
    "title": "The night crew grows| !Discord !lurk | 🐉🧟",
    "viewer_count": 4,
    "started_at": "2026-04-17T00:58:08Z",
    "language": "en",
    "thumbnail_url": "https://static-cdn.jtvnw.net/previews-ttv/live_user_dracolicheren-{width}x{height}.jpg",
    "tag_ids": [],
    "tags": [
      "English",
      "ENVtuber",
      "sillyvtuber",
      "MaleVtuber",
      "VTuberUprising",
      "dragonvtuber",
      "undeadvtuber",
      "Horror"
    ],
    "is_mature": false,
    "profile_image_url": "https://static-cdn.jtvnw.net/jtv_user_pictures/e9ccd82f-2952-4bdd-aef2-41755db04f69-profile_image-300x300.png"
  },
  {
    "id": "318809989466",
    "user_id": "193636646",
    "user_login": "captainyeeticus",
    "user_name": "captainyeeticus",
    "game_id": "67824",
    "game_name": "Tomodachi Life",
    "type": "live",
    "title": "Too broke for Living the Dream, but hey, at least we still have the 3DS version! [ENPNGTuber] | !discord !hello",
    "viewer_count": 2,
    "started_at": "2026-04-17T00:23:53Z",
    "language": "en",
    "thumbnail_url": "https://static-cdn.jtvnw.net/previews-ttv/live_user_captainyeeticus-{width}x{height}.jpg",
    "tag_ids": [],
    "tags": [
      "lgbt",
      "gremlin",
      "artist",
      "author",
      "transgender",
      "vtuber",
      "pngtuber",
      "envtuber",
      "English"
    ],
    "is_mature": false,
    "profile_image_url": "https://static-cdn.jtvnw.net/jtv_user_pictures/1d86efb6-3440-45f1-aa15-38be19b0cfdd-profile_image-300x300.png"
  },
  {
    "id": "318294709344",
    "user_id": "39084354",
    "user_login": "enigmaticslime",
    "user_name": "enigmaticslime",
    "game_id": "2080936601",
    "game_name": "Mouse: P.I. For Hire",
    "type": "live",
    "title": "Time for the daring adventure of Enigmaticslime PI!",
    "viewer_count": 1,
    "started_at": "2026-04-17T00:42:34Z",
    "language": "en",
    "thumbnail_url": "https://static-cdn.jtvnw.net/previews-ttv/live_user_enigmaticslime-{width}x{height}.jpg",
    "tag_ids": [],
    "tags": [
      "LGBTAQIAplus",
      "SlimeVtuber",
      "prettydumb",
      "Easilydistracted",
      "KindOfReallyDumb",
      "TwoBrainCells",
      "nonbinanry",
      "English",
      "Mature",
      "18pluschannel"
    ],
    "is_mature": true,
    "profile_image_url": "https://static-cdn.jtvnw.net/jtv_user_pictures/35a9b99d-c953-4959-b2f0-db5a134e5b5d-profile_image-300x300.png"
  }
]