[
  {
    "id": "317223494615",
    "user_id": "133400606",
    "user_login": "slushieghost",
    "user_name": "SlushieGhost",
    "game_id": "27471",
    "game_name": "Minecraft",
    "type": "live",
    "title": "\u2727 What kind of fever dream is happening today? | adVenture: Ascension ep 6 \u2727 !lurk !merch !throne !clip",
    "viewer_count": 23,
    "started_at": "2026-03-27T22:54:23Z",
    "language": "en",
    "thumbnail_url": "https://static-cdn.jtvnw.net/previews-ttv/live_user_slushieghost-{width}x{height}.jpg",
    "tag_ids": [],
    "tags": [
      "Comfy",
      "LGBT",
      "Nonbinary",
      "VTuber",
      "SpanishAndEnglish",
      "ENVtuber",
      "Hispanic",
      "ADHD",
      "Bilingual",
      "adVAscension"
    ],
    "is_mature": true,
    "profile_image_url": "https://static-cdn.jtvnw.net/jtv_user_pictures/7f48840f-5f89-432b-981b-c1e575eccae8-profile_image-300x300.png"
  },
  {
    "id": "318450170202",
    "user_id": "884094552",
    "user_login": "magicteahouse",
    "user_name": "MagicTeaHouse",
    "game_id": "1081998272",
    "game_name": "PEAK",
    "type": "live",
    "title": "[18+] Solo + Chat Spawns?? I ain't making past the beach.... [Crowd Control Peak] | !throne !socials !lurk !discord",
    "viewer_count": 6,
    "started_at": "2026-03-27T23:04:33Z",
    "language": "en",
    "thumbnail_url": "https://static-cdn.jtvnw.net/previews-ttv/live_user_magicteahouse-{width}x{height}.jpg",
    "tag_ids": [],
    "tags": [
      "Vtuber",
      "ENVtuber",
      "girl",
      "LGBT",
      "English",
      "Canadian",
      "cozygaming",
      "CrowdControl",
      "peak",
      "PEAKmodded"
    ],
    "is_mature": true,
    "profile_image_url": "https://static-cdn.jtvnw.net/jtv_user_pictures/36487cf1-f49e-4a62-bfd6-0554b21f3a9d-profile_image-300x300.png"
  },
  {
    "id": "317887055452",
    "user_id": "1142519722",
    "user_login": "triagesylphiel",
    "user_name": "TriageSylphiel",
    "game_id": "512953",
    "game_name": "ELDEN RING",
    "type": "live",
    "title": "I DON'T REMEMBER WHAT WAS HAPPENING!!! | !Clip !Discord",
    "viewer_count": 4,
    "started_at": "2026-03-27T23:11:54Z",
    "language": "en",
    "thumbnail_url": "https://static-cdn.jtvnw.net/previews-ttv/live_user_triagesylphiel-{width}x{height}.jpg",
    "tag_ids": [],
    "tags": [
      "Vtuber",
      "English",
      "birdtuber",
      "peepeepoopoo",
      "LGBTQFriendly",
      "indievtuber",
      "ENVtuber",
      "vtubers",
      "CloacaKing"
    ],
    "is_mature": false,
    "profile_image_url": "https://static-cdn.jtvnw.net/jtv_user_pictures/656f0ac1-dda4-421b-ba6c-5872f45058ce-profile_image-300x300.jpeg"
  },
  {
    "id": "318554394971",
    "user_id": "405460237",
    "user_login": "nokoadragon",
    "user_name": "NokoADragon",
    "game_id": "75115",
    "game_name": "Mewgenics",
    "type": "live",
    "title": "Tasty Legs and Crispy Thighs. My cats are going to break || Mewgenics (!lurk, !links, !discord)",
    "viewer_count": 3,
    "started_at": "2026-03-27T22:00:06Z",
    "language": "en",
    "thumbnail_url": "https://static-cdn.jtvnw.net/previews-ttv/live_user_nokoadragon-{width}x{height}.jpg",
    "tag_ids": [],
    "tags": [
      "English",
      "Eldritch",
      "EnPNGTuber",
      "ADHD",
      "LGBTQFriendly",
      "Vtuber"
    ],
    "is_mature": false,
    "profile_image_url": "https://static-cdn.jtvnw.net/jtv_user_pictures/0d641617-28b1-41b5-a00a-254dc59d3ca0-profile_image-300x300.png"
  },
  {
    "id": "316302127586",
    "user_id": "85124538",
    "user_login": "vaneros_lunpo",
    "user_name": "Vaneros_Lunpo",
    "game_id": "532988445",
    "game_name": "PowerWash Simulator 2",
    "type": "live",
    "title": "[18+] Spraying and Singing, The chillest of Chill",
    "viewer_count": 3,
    "started_at": "2026-03-27T21:01:33Z",
    "language": "en",
    "thumbnail_url": "https://static-cdn.jtvnw.net/previews-ttv/live_user_vaneros_lunpo-{width}x{height}.jpg",
    "tag_ids": [],
    "tags": [
      "Pirate",
      "English",
      "Penguin",
      "Vtuber",
      "18maturelanguage",
      "18PlusStreamer"
    ],
    "is_mature": true,
    "profile_image_url": "https://static-cdn.jtvnw.net/jtv_user_pictures/f5d8f57e-c41d-412f-a00b-6d48e5ba4b86-profile_image-300x300.png"
  },
  {
    "id": "318553602523",
    "user_id": "1185217143",
    "user_login": "zecosmiccrow",
    "user_name": "ZeCosmicCrow",
    "game_id": "2085980140",
    "game_name": "Lethal Company",
    "type": "live",
    "title": "BIRB WEEK COLLAB 2! Let's get Lethal! w/ @pawchivt @hikikomorrivt @beanofetg @akira_san4 @kiracrowe \u2307 18+ \u2307 !discord !social",
    "viewer_count": 3,
    "started_at": "2026-03-27T21:11:16Z",
    "language": "en",
    "thumbnail_url": "https://static-cdn.jtvnw.net/previews-ttv/live_user_zecosmiccrow-{width}x{height}.jpg",
    "tag_ids": [],
    "tags": [
      "Vtuber",
      "English",
      "Crow",
      "MaleVtuber",
      "Cosmic",
      "Comfy",
      "Chaotic",
      "Yapper",
      "chill",
      "Chatty"
    ],
    "is_mature": false,
    "profile_image_url": "https://static-cdn.jtvnw.net/jtv_user_pictures/836df522-58d3-4a0e-a534-9b1695156746-profile_image-300x300.jpeg"
  },
  {
    "id": "318388478169",
    "user_id": "1229718627",
    "user_login": "huanyavt",
    "user_name": "HuanyaVT",
    "game_id": "1280007947",
    "game_name": "Limbus Company",
    "type": "live",
    "title": "[18+] Tonight, the world loses a Futch Lesbian baddie... | Limbus Company | !lurk !throne !tip !discord",
    "viewer_count": 1,
    "started_at": "2026-03-27T23:00:21Z",
    "language": "en",
    "thumbnail_url": "https://static-cdn.jtvnw.net/previews-ttv/live_user_huanyavt-{width}x{height}.jpg",
    "tag_ids": [],
    "tags": [
      "dinosaur",
      "Dinotuber",
      "ADHD",
      "Vtuber",
      "LGBTQIAPIus",
      "ENVTubers",
      "18pluschannel",
      "pngtuber",
      "English",
      "Scuff"
    ],
    "is_mature": false,
    "profile_image_url": "https://static-cdn.jtvnw.net/jtv_user_pictures/9649510b-f84f-4fb5-9f9c-d50ef3159a51-profile_image-300x300.png"
  }
]