[
  {
    "id": "316208612599",
    "user_id": "133400606",
    "user_login": "slushieghost",
    "user_name": "SlushieGhost",
    "game_id": "27471",
    "game_name": "Minecraft",
    "type": "live",
    "title": "✧ Dungeons, Dragons...and farming?? | adVenture: Ascension ep 2 ✧ !lurk !merch !throne !clip",
    "viewer_count": 23,
    "started_at": "2026-03-22T23:00:52Z",
    "language": "en",
    "thumbnail_url": "https://static-cdn.jtvnw.net/previews-ttv/live_user_slushieghost-{width}x{height}.jpg",
    "tag_ids": [],
    "tags": [
      "Comfy",
      "LGBT",
      "Nonbinary",
      "VTuber",
      "SpanishAndEnglish",
      "ENVtuber",
      "Hispanic",
      "ADHD",
      "Bilingual",
      "adVAscension"
    ],
    "is_mature": true,
    "profile_image_url": "https://static-cdn.jtvnw.net/jtv_user_pictures/7f48840f-5f89-432b-981b-c1e575eccae8-profile_image-300x300.png"
  },
  {
    "id": "318304521305",
    "user_id": "952513348",
    "user_login": "cabbytat",
    "user_name": "CabbyTat",
    "game_id": "27471",
    "game_name": "Minecraft",
    "type": "live",
    "title": "[18+] CHAT VS. CABBY AND @tinypixiedae (!clip)",
    "viewer_count": 14,
    "started_at": "2026-03-22T20:50:57Z",
    "language": "en",
    "thumbnail_url": "https://static-cdn.jtvnw.net/previews-ttv/live_user_cabbytat-{width}x{height}.jpg",
    "tag_ids": [],
    "tags": [
      "Catboy",
      "BoyWife",
      "Anime",
      "Comfy",
      "LGBTQ",
      "English",
      "femboy",
      "Vtuber",
      "Chatting",
      "BackseatGamingAllowed"
    ],
    "is_mature": false,
    "profile_image_url": "https://static-cdn.jtvnw.net/jtv_user_pictures/653014f5-f4ef-4b21-ab71-333a28ca8cc8-profile_image-300x300.jpeg"
  },
  {
    "id": "315432821353",
    "user_id": "95084465",
    "user_login": "deltarious5",
    "user_name": "Deltarious5",
    "game_id": "490377",
    "game_name": "Sea of Thieves",
    "type": "live",
    "title": "fites? at nites? BRING IT ON! [!discord] [!dubby] [18+]",
    "viewer_count": 1,
    "started_at": "2026-03-22T20:17:11Z",
    "language": "en",
    "thumbnail_url": "https://static-cdn.jtvnw.net/previews-ttv/live_user_deltarious5-{width}x{height}.jpg",
    "tag_ids": [],
    "tags": [
      "NewZealand",
      "Casual",
      "ADHD",
      "English",
      "Vtuber",
      "NoBackseatingUnlessAsked",
      "18pluschannel",
      "cosplayer",
      "crossdresser",
      "Anime"
    ],
    "is_mature": false,
    "profile_image_url": "https://static-cdn.jtvnw.net/jtv_user_pictures/bae917c1-464e-4eae-a727-5d4b761fac21-profile_image-300x300.png"
  }
]